setup.py
flask_simple_alchemy/__init__.py
flask_simple_alchemy/factories.py
flask_simple_alchemy/factory_helpers.py
flask_simple_alchemy/relator.py
flask_simple_alchemy.egg-info/PKG-INFO
flask_simple_alchemy.egg-info/SOURCES.txt
flask_simple_alchemy.egg-info/dependency_links.txt
flask_simple_alchemy.egg-info/not-zip-safe
flask_simple_alchemy.egg-info/requires.txt
flask_simple_alchemy.egg-info/top_level.txt