Metadata-Version: 1.0
Name: flask-simple-alchemy
Version: 0.3.0
Summary: A Simplification of SQLAlchemy's declarative using Flask-SQLAlchemy
Home-page: https://github.com/jlgoldb2/flask-simple-alchemy
Author: Jason Goldberger
Author-email: jlgoldb2@asu.edu
License: MIT
Platform: any
